README.txt
plone4.cfg
setup.cfg
setup.py
babble/__init__.py
babble.demo.egg-info/PKG-INFO
babble.demo.egg-info/SOURCES.txt
babble.demo.egg-info/dependency_links.txt
babble.demo.egg-info/entry_points.txt
babble.demo.egg-info/namespace_packages.txt
babble.demo.egg-info/not-zip-safe
babble.demo.egg-info/paster_plugins.txt
babble.demo.egg-info/requires.txt
babble.demo.egg-info/top_level.txt
babble/demo/__init__.py
babble/demo/configure.zcml
babble/demo/setuphandlers.py
babble/demo/tests.py
babble/demo/profiles/default/babble.demo_marker.txt
babble/demo/profiles/default/metadata.xml
docs/HISTORY.txt
docs/INSTALL.txt
docs/LICENSE.GPL
docs/LICENSE.txt