Metadata-Version: 1.0
Name: babble.demo
Version: 0.1
Summary: Creates a demo Babble instant messaging setup for Plone
Home-page: http://svn.plone.org/svn/collective/
Author: JC Brand
Author-email: brand@syslab.com
License: GPL
Keywords: babble messaging demo plone
Platform: UNKNOWN
Classifier: Framework :: Plone
Classifier: Programming Language :: Python
